mondaytoframe/__init__.py
mondaytoframe/io.py
mondaytoframe/model.py
mondaytoframe/parsers_for_frame.py
mondaytoframe/parsers_for_monday.py
mondaytoframe/py.typed
mondaytoframe-0.2.1.dist-info/METADATA
mondaytoframe-0.2.1.dist-info/WHEEL
mondaytoframe-0.2.1.dist-info/licenses/LICENSE
mondaytoframe-0.2.1.dist-info/RECORD
