Metadata-Version: 2.4
Name: mondaytoframe
Version: 0.2.1
Summary: This python package helps converting data between the Monday API and Dataframes
Project-URL: Homepage, https://github.com/boukepostma/mondaytoframe
Project-URL: Repository, https://github.com/boukepostma/mondaytoframe.git
Project-URL: Documentation, https://github.com/boukepostma/mondaytoframe#readme
Project-URL: Issues, https://github.com/boukepostma/mondaytoframe/issues
Author-email: Bouke Postma <33422940+boukepostma@users.noreply.github.com>
License-File: LICENSE
Requires-Python: >=3.12
Requires-Dist: monday>=2.0.1
Requires-Dist: pandas>=2.2.3
Requires-Dist: phonenumbers>=8.13.55
Requires-Dist: pycountry>=24.6.1
Requires-Dist: pydantic-extra-types>=2.10.2
Requires-Dist: pydantic>=2.10.6
Requires-Dist: requests>=2.32.3
